{"guide_chart.md":"b88f5ac5","guide_construction.md":"db20370c","guide_deploy.md":"30a809e0","guide_environment-variables.md":"80413053","guide_eslint.md":"fa1b7995","guide_formatter.md":"d77b63f9","guide_i18n.md":"618e92e4","guide_icon.md":"309fda4a","guide_index.md":"8382e9b5","guide_layout.md":"3a65507d","guide_migration.md":"37bea77f","guide_mock.md":"4da56b77","guide_permission.md":"4fc0ef30","guide_plugins.md":"8264124c","guide_pnpm.md":"1da65b06","guide_router.md":"ef74306f","guide_style.md":"0ea9b116","guide_testing.md":"e5ad4d91","guide_theme.md":"a83c3e87","guide_typescript.md":"77dacf77","guide_why.md":"f96718fe","index.md":"122e4885"}
