{"guide_chart.md":"f474dad0","guide_deploy.md":"50b55bb3","guide_environment-variables.md":"aa9f8d44","guide_eslint.md":"804afb9f","guide_formatter.md":"62340115","guide_i18n.md":"dd5bbf7a","guide_icon.md":"6c6dc625","guide_index.md":"1fff0f92","guide_migration.md":"87796c56","guide_mock.md":"171dc73b","guide_permission.md":"16934a17","guide_plugins.md":"6ac470e2","guide_router.md":"98d26f04","guide_style.md":"fc96d9cf","guide_testing.md":"d2a7f912","guide_theme.md":"0523bc46","guide_typescript.md":"95d8f025","guide_why.md":"a3b96d46","index.md":"06b4748d"}
