{"guide_chart.md":"26ed58e3","guide_construction.md":"690ad151","guide_deploy.md":"d009c456","guide_environment-variables.md":"587c675e","guide_eslint.md":"e4022e87","guide_formatter.md":"e0591ed6","guide_i18n.md":"c45d6b73","guide_icon.md":"95cd3b11","guide_index.md":"d0253124","guide_layout.md":"f331d06d","guide_migration.md":"b12932b2","guide_mock.md":"9c56a16d","guide_permission.md":"2793e5be","guide_plugins.md":"d1acfd1f","guide_pnpm.md":"9146ee64","guide_router.md":"d9fb9c6a","guide_style.md":"d767153c","guide_testing.md":"25f9d156","guide_theme.md":"392bb75f","guide_typescript.md":"4e4416d4","guide_why.md":"87d1feb7","index.md":"088ae90e"}
